factor/__init__.py
factor/utils.py
zw_backtrader/__init__.py
zw_backtrader/demo.py
zw_backtrader/zw_cerebro.py
zw_backtrader/zw_option.py
zw_backtrader/data/__init__.py
zw_backtrader/strategy/__init__.py
zw_backtrader/strategy/strategy.py
zw_backtrader/trade/__init__.py
zw_backtrader/trade/trade_detail.py
zwkit/__init__.py
zwkit/dataset.py
zwkit/date_kit.py
zwkit/ddb_kit.py
zwkit/ddbkit.py
zwkit/factor_analyse.py
zwkit/gp_kit.py
zwkit/http_kit.py
zwkit/num_kit.py
zwkit/path_kit.py
zwkit-0.4.58.dist-info/LICENSE
zwkit-0.4.58.dist-info/METADATA
zwkit-0.4.58.dist-info/WHEEL
zwkit-0.4.58.dist-info/top_level.txt
zwkit-0.4.58.dist-info/RECORD
