Metadata-Version: 2.1
Name: zwkit
Version: 0.4.58
Summary: zwhy kit for python
Author: bomu
Author-email: zhaowwwjian@gmail.com
License: Apache-2.0 license
Platform: any
Requires-Python: >=3.6
License-File: LICENSE
Requires-Dist: backtrader
Requires-Dist: dolphindb
Requires-Dist: numpy
Requires-Dist: torch
